Codado-0.8.0.data/scripts/jentemplate
codado/__init__.py
codado/_version.py
codado/hotedit.py
codado/py.py
codado/tx.py
codado/dockerish/__init__.py
codado/dockerish/event.py
codado/test/__init__.py
codado/test/test_dockerish_event.py
codado/test/test_hotedit.py
codado/test/test_py.py
codado/test/test_tx.py
Codado-0.8.0.dist-info/LICENSE
Codado-0.8.0.dist-info/METADATA
Codado-0.8.0.dist-info/WHEEL
Codado-0.8.0.dist-info/top_level.txt
Codado-0.8.0.dist-info/RECORD
